tupledict
