Metadata-Version: 2.1
Name: tupledict
Version: 1.1
Summary: A multi-key dictionary with wildcard lookup.
Home-page: UNKNOWN
Author: Anton Dries
Author-email: anton.dries@gmail.com
License: UNKNOWN
Platform: UNKNOWN
Classifier: Programming Language :: Python :: 3
Classifier: License :: OSI Approved :: MIT License
Classifier: Operating System :: OS Independent
Requires-Python: >=3.5
